notte_integrations/__init__.py
notte_integrations/py.typed
notte_integrations/credentials/README.md
notte_integrations/credentials/__init__.py
notte_integrations/notifiers/README.md
notte_integrations/notifiers/__init__.py
notte_integrations/notifiers/discord.py
notte_integrations/notifiers/mail.py
notte_integrations/notifiers/slack.py
notte_integrations/sessions/__init__.py
notte_integrations/sessions/anchor.py
notte_integrations/sessions/browserbase.py
notte_integrations/sessions/cdp_session.py
notte_integrations/sessions/hyperbrowser.py
notte_integrations/sessions/notte.py
notte_integrations/sessions/steel.py
notte_integrations-1.8.3.dist-info/METADATA
notte_integrations-1.8.3.dist-info/WHEEL
notte_integrations-1.8.3.dist-info/RECORD
